{
	"graph": "maindocument",
	"proptitle": "http://w3id.org/roh/title",
	"propdescription": "",
	"rdftype": "http://w3id.org/roh/MainDocument",
	"sections": [
		{
			"title": {
				"es": "Publicación principal"
			},
			"rows": [
				{
					"properties": [
						{
							"title": {
								"es": "Nombre de la publicación"
							},
							"required": true,
							"property": "http://w3id.org/roh/title",
							"width": 3
						}
					]
				},
				{
					"properties": [
						{
							"title": {
								"es": "ISBN"
							},
							"placeholder": {
								"es": "Introduce el ISBN"
							},
							"required": false,
							"property": "http://purl.org/ontology/bibo/isbn",
							"width": 1
						},
						{
							"title": {
								"es": "ISSN"
							},
							"placeholder": {
								"es": "Introduce el ISSN"
							},
							"required": false,
							"property": "http://purl.org/ontology/bibo/issn",
							"width": 1
						},
						{
							"title": {
								"es": "Editorial"
							},
							"placeholder": {
								"es": "Introduce la editorial"
							},
							"required": false,
							"property": "http://purl.org/ontology/bibo/editor",
							"width": 1
						}
					]
				},
				{
					"properties": [
						{
							"title": {
								"es": "Tipo de soporte"
							},
							"required": false,
							"property": "http://w3id.org/roh/format",
							"combo": {
								"rdftype": "http://w3id.org/roh/DocumentFormat",
								"graph": "documentformat",
								"property": {
									"property": "http://purl.org/dc/elements/1.1/title"
								}
							},
							"type": "selectCombo",
							"width": 1
						}
					]
				},
				{
					"properties": [
						{
							"property": "http://w3id.org/roh/impactIndex",
							"type": "auxEntity",
							"title": {
								"es": "Índice de impacto"
							},
							"multiple": true,
							"width": 3,
							"auxEntityData": {
								"rdftype": "http://w3id.org/roh/ImpactIndex",
								"propertyOrder": "http://w3id.org/roh/year",
								"propertyTitle": {
									"property": "http://w3id.org/roh/impactSource"
								},
								"properties": [
									{
										"name": {
											"es": "Fuente de impacto"
										},
										"child": {
											"property": "http://w3id.org/roh/impactSource",
											"graph": "referencesource",
											"child": {
												"property": "http://purl.org/dc/elements/1.1/title"
											}
										}
									},
									{
										"name": {
											"es": "Otros"
										},
										"child": {
											"property": "http://w3id.org/roh/impactSourceOther"
										}
									},
									{
										"name": {
											"es": "Categoría"
										},
										"child": {
											"property": "http://w3id.org/roh/impactSource",
											"graph": "impactindexcategory",
											"child": {
												"property": "http://purl.org/dc/elements/1.1/title"
											}
										}
									},
									{
										"name": {
											"es": "Índice de impacto"
										},
										"child": {
											"property": "http://w3id.org/roh/impactIndexInYear"
										}
									},
									{
										"name": {
											"es": "Posición de publicación"
										},
										"child": {
											"property": "http://w3id.org/roh/publicationPosition"
										}
									},
									{
										"name": {
											"es": "Núm. revistas en cat."
										},
										"child": {
											"property": "http://w3id.org/roh/journalNumberInCat"
										}
									},
									{
										"name": {
											"es": "Revista dentro del 25%"
										},
										"child": {
											"property": "http://w3id.org/roh/journalTop25"
										}
									},
									{
										"name": {
											"es": "Año"
										},
										"child": {
											"property": "http://w3id.org/roh/year"
										}
									}
								],
								"rows": [
									{
										"properties": [
											{
												"title": {
													"es": "Fuente de impacto"
												},
												"property": "http://purl.org/dc/elements/1.1/type",
												"combo": {
													"rdftype": "http://purl.org/ontology/bibo/ReferenceSource",
													"graph": "referencesource",
													"property": {
														"property": "http://purl.org/dc/elements/1.1/title"
													}
												},
												"type": "selectCombo",
												"width": 1
											},
											{
												"title": {
													"es": "Otros"
												},
												"placeholder": {
													"es": "Introduce la fuente de impacto"
												},
												"required": false,
												"property": "http://w3id.org/roh/impactSourceOther",
												"width": 1
											}
										]
									},
									{
										"properties": [
											{
												"title": {
													"es": "Categoría"
												},
												"property": "http://purl.org/ontology/bibo/impactCategory",
												"combo": {
													"rdftype": "http://purl.org/ontology/bibo/ImpactIndexCategory",
													"graph": "impactindexcategory",
													"property": {
														"property": "http://purl.org/dc/elements/1.1/title"
													}
												},
												"type": "selectCombo",
												"width": 2
											},
											{
												"title": {
													"es": "Índice de impacto"
												},
												"placeholder": {
													"es": "Introduce el índice de impacto"
												},
												"required": false,
												"property": "http://w3id.org/roh/impactIndexInYear",
												"width": 1
											}
										]
									},
									{
										"properties": [
											{
												"title": {
													"es": "Posición de publicación"
												},
												"placeholder": {
													"es": "Introduce la posición de publicación"
												},
												"required": false,
												"property": "http://w3id.org/roh/publicationPosition",
												"width": 1
											},
											{
												"title": {
													"es": "Num. revistas en cat."
												},
												"placeholder": {
													"es": "Introduce el número de revistas en su categoría"
												},
												"required": false,
												"property": "http://w3id.org/roh/journalNumberInCat",
												"width": 1
											},
											{
												"title": {
													"es": "Revista dentro del 25%"
												},
												"required": false,
												"property": "http://w3id.org/roh/journalTop25",
												"width": 1
											}
										]
									}
								]
							}
						}
					]
				}
			]
		}
	]
}